agent-runtime/__init__.py
autogen-agent/__init__.py
autogen-agentchat/__init__.py
autogen-agentflow/__init__.py
autogen-core/__init__.py
autogen-flow/__init__.py
autogen-gemini/__init__.py
autogen-kernel/__init__.py
autogen-langchain/__init__.py
autogen-magentic/__init__.py
autogen-magentic-one/__init__.py
autogen-mcp/__init__.py
autogen-mistral/__init__.py
autogen-next/__init__.py
autogen-openai/__init__.py
autogen-process/__init__.py
autogen-samples/__init__.py
autogen-semantic-kernel/__init__.py
autogen-sk/__init__.py
autogen-studio/__init__.py
autogen-team-one/__init__.py
gymgen/__init__.py
magentic-one/__init__.py
pyautogen-core/__init__.py
webby-agent/__init__.py
gymgen-0.0.1.dist-info/LICENSE
gymgen-0.0.1.dist-info/METADATA
gymgen-0.0.1.dist-info/WHEEL
gymgen-0.0.1.dist-info/top_level.txt
gymgen-0.0.1.dist-info/RECORD
