Metadata-Version: 2.1
Name: gymgen
Version: 0.0.1
Summary: GymGen
Home-page: https://github.com/microsoft/autogen
Author: AutoGen Developers
Author-email: your_email@example.com
Classifier: Programming Language :: Python :: 3
Classifier: License :: OSI Approved :: MIT License
Classifier: Operating System :: OS Independent
Requires-Python: >=3.6
License-File: LICENSE
